wagtail_seo_report/__init__.py
wagtail_seo_report/settings.py
wagtail_seo_report/views.py
wagtail_seo_report/wagtail_hooks.py
wagtail_seo_report/static/wagtail_seo_report/core.css
wagtail_seo_report/templates/wagtail_seo_report/seo_score_report_results.html
wagtail_seo_report/templates/wagtail_seo_report/wagtail_seo_report.svg
wagtail_seo_report/templates/wagtail_seo_report/listing/_list_seo_page_report.html
wagtail_seo_report-0.1.0.dist-info/METADATA
wagtail_seo_report-0.1.0.dist-info/WHEEL
wagtail_seo_report-0.1.0.dist-info/top_level.txt
wagtail_seo_report-0.1.0.dist-info/RECORD
