Metadata-Version: 2.1
Name: wagtail-seo-report
Version: 0.1.0
Author: R.Moorman <rob@vicktor.nl>
Classifier: Environment :: Web Environment
Classifier: Operating System :: Unix
Classifier: Programming Language :: Python :: 3
Classifier: Framework :: Django
Classifier: Framework :: Wagtail :: 6
Requires-Dist: django>=4
Requires-Dist: wagtail>=6
Provides-Extra: test
Requires-Dist: black; extra == "test"
Requires-Dist: factory-boy; extra == "test"
Requires-Dist: flake8; extra == "test"
Requires-Dist: isort; extra == "test"
Requires-Dist: pytest; extra == "test"
Requires-Dist: pytest-django; extra == "test"
